edbotstudio/__init__.py
edbotstudio/client.py
edbotstudio/robotis.py
edbotstudio-1.0.1.dist-info/LICENCE
edbotstudio-1.0.1.dist-info/METADATA
edbotstudio-1.0.1.dist-info/WHEEL
edbotstudio-1.0.1.dist-info/top_level.txt
edbotstudio-1.0.1.dist-info/RECORD
