Metadata-Version: 2.1
Name: edbotstudio
Version: 1.0.1
Summary: A Python client API for Edbot Studio
Home-page: https://github.com/edbotstudio/client-python
Author: Clive Haworth
Author-email: clive@ed.bot
License: MIT
Project-URL: Bug Tracker, https://github.com/edbotstudio/client-python/issues
Platform: UNKNOWN
Classifier: Programming Language :: Python :: 3
Classifier: License :: OSI Approved :: MIT License
Classifier: Operating System :: OS Independent
Requires-Python: >=3
Requires-Dist: ws4py
Requires-Dist: pydash
